battlecat/__init__.py
battlecat/celery.py
battlecat/settings.py
battlecat/urls.py
battlecat/wsgi.py
battlecat/core/__init__.py
battlecat/core/admin.py
battlecat/core/apps.py
battlecat/core/models.py
battlecat/core/tasks.py
battlecat/core/tests.py
battlecat/core/urls.py
battlecat/core/views.py
battlecat/core/migrations/__init__.py
battlecat-0.1.0.dist-info/DESCRIPTION.rst
battlecat-0.1.0.dist-info/METADATA
battlecat-0.1.0.dist-info/RECORD
battlecat-0.1.0.dist-info/WHEEL
battlecat-0.1.0.dist-info/metadata.json
battlecat-0.1.0.dist-info/top_level.txt
