Metadata-Version: 2.0
Name: battlecat
Version: 0.1.0
Summary: Django-based double entry accounting based on Hordak
Home-page: https://github.com/adamcharnock/battlecat
Author: Adam Charnock
Author-email: adam@adamcharnock.com
License: MIT
Platform: UNKNOWN
Requires-Dist: Django (>=1.8)
Requires-Dist: celery (==4.0.2)
Requires-Dist: dj-database-url
Requires-Dist: dj-static
Requires-Dist: django-adminlte2
Requires-Dist: django-bootstrap3 (>=7)
Requires-Dist: django-celery-beat (==1.0.1)
Requires-Dist: django-celery-results (==1.0.1)
Requires-Dist: django-choices (==1.4.4)
Requires-Dist: django-extensions
Requires-Dist: django-model-utils (>=2.6)
Requires-Dist: django-redis (==4.6.0)
Requires-Dist: gunicorn
Requires-Dist: kombu (==4.0.2)
Requires-Dist: path.py
Requires-Dist: psycopg2
Requires-Dist: redis (==2.10.5)
Requires-Dist: requests (==2.12.4)
Requires-Dist: requests-mock (==1.2.0)
